cmt/__init__.py
cmt/a_converter.py
cmt/a_map.py
cmt/codec.py
cmt/convert.py
cmt/meta.py
cmt/utils.py
cmt/cmap/__init__.py
cmt/cmap/a_cmap.py
cmt/cmap/a_entity.py
cmt/cmap/v0/__init__.py
cmt/cmap/v0/cmap.py
cmt/cmap/v0/entities.py
cmt/cmap/v0/medal_time.py
cmt/cmap/v1/__init__.py
cmt/cmap/v1/checkpoint_time.py
cmt/cmap/v1/cmap.py
cmt/cmap/v1/entities.py
cmt/cmap/v2/__init__.py
cmt/cmap/v2/checkpoint_time.py
cmt/cmap/v2/cmap.py
cmt/cmap/v2/entities.py
cmt/converter/__init__.py
cmt/converter/cmap_v0.py
cmt/converter/cmap_v1.py
cmt/converter/cmap_v2.py
cmt/converter/ecmap_v0.py
cmt/converter/ecmap_v1.py
cmt/converter/ecmap_v2.py
cmt/converter/ecmap_v4.py
cmt/cs/__init__.py
cmt/cs/main.py
cmt/ecmap/__init__.py
cmt/ecmap/a_ecmap.py
cmt/ecmap/v0/__init__.py
cmt/ecmap/v0/ecmap.py
cmt/ecmap/v1/__init__.py
cmt/ecmap/v1/ecmap.py
cmt/ecmap/v2/__init__.py
cmt/ecmap/v2/ecmap.py
cmt/ecmap/v4/__init__.py
cmt/ecmap/v4/ecmap.py
CMT-0.4.0.dist-info/METADATA
CMT-0.4.0.dist-info/WHEEL
CMT-0.4.0.dist-info/entry_points.txt
CMT-0.4.0.dist-info/top_level.txt
CMT-0.4.0.dist-info/zip-safe
CMT-0.4.0.dist-info/RECORD
