Metadata-Version: 2.1
Name: CMT
Version: 0.4.0
Summary: Celeria Map Toolkit, can convert different map formats from one into another.
Home-page: https://github.com/IceflowRE/cmt
Author: Iceflower S
Author-email: iceflower@gmx.de
License: MIT
Keywords: map toolkit
Platform: UNKNOWN
Classifier: Programming Language :: Python :: 3.7
Classifier: License :: OSI Approved :: MIT License
Classifier: Development Status :: 4 - Beta
Classifier: Operating System :: OS Independent
Classifier: Intended Audience :: Developers
Classifier: Natural Language :: English
Requires-Python: >=3.7
Provides-Extra: dev
Requires-Dist: flake8 (>=3.9.2) ; extra == 'dev'
Requires-Dist: pylint (>=2.11.1) ; extra == 'dev'
Requires-Dist: pyroma (>=3.2) ; extra == 'dev'
Requires-Dist: pytest (>=6.2.5) ; extra == 'dev'
Requires-Dist: pytest-cov (>=2.12.1) ; extra == 'dev'
Requires-Dist: setuptools (>=58.2.0) ; extra == 'dev'
Requires-Dist: Sphinx (>=4.2.0) ; extra == 'dev'
Requires-Dist: sphinx-autodoc-typehints (>=1.12.0) ; extra == 'dev'
Requires-Dist: sphinx-rtd-theme (>=1.0.0) ; extra == 'dev'
Requires-Dist: twine (>=3.4.2) ; extra == 'dev'
Requires-Dist: wheel (>=0.37.0) ; extra == 'dev'
